{
  "family": "Sofia Sans Semi Condensed",
  "slug": "sofia-sans-semi-condensed",
  "categories": [
    "sans-serif"
  ],
  "subsets": [
    "cyrillic",
    "cyrillic-ext",
    "greek",
    "latin",
    "latin-ext"
  ],
  "variants": [
    "100",
    "200",
    "300",
    "regular",
    "500",
    "600",
    "700",
    "800",
    "900",
    "100italic",
    "200italic",
    "300italic",
    "italic",
    "500italic",
    "600italic",
    "700italic",
    "800italic",
    "900italic"
  ],
  "version": "v8",
  "lastModified": "2025-09-10"
}
